fortnox/__init__.py
fortnox/client.py
fortnox/coercion.py
fortnox/configuration.py
fortnox/errors.py
fortnox/http_client.py
fortnox/services/__init__.py
fortnox/services/absence_transaction_services.py
fortnox/services/access_token_service.py
fortnox/services/account_chart_services.py
fortnox/services/account_services.py
fortnox/services/archive_services.py
fortnox/services/article_file_connection_services.py
fortnox/services/article_services.py
fortnox/services/asset_file_connection_services.py
fortnox/services/asset_services.py
fortnox/services/asset_type_services.py
fortnox/services/attendance_transaction_services.py
fortnox/services/company_information_services.py
fortnox/services/company_settings_services.py
fortnox/services/contract_accrual_services.py
fortnox/services/contract_services.py
fortnox/services/contract_template_services.py
fortnox/services/cost_center_services.py
fortnox/services/currency_services.py
fortnox/services/customer_services.py
fortnox/services/employee_services.py
fortnox/services/expense_services.py
fortnox/services/financial_year_services.py
fortnox/services/inbox_services.py
fortnox/services/invoice_accrual_services.py
fortnox/services/invoice_file_connection_services.py
fortnox/services/invoice_payment_services.py
fortnox/services/invoice_services.py
fortnox/services/label_services.py
fortnox/services/locked_period_services.py
fortnox/services/modes_of_payment_services.py
fortnox/services/nox_finans_invoice_services.py
fortnox/services/offer_services.py
fortnox/services/order_services.py
fortnox/services/predefined_account_services.py
fortnox/services/predefined_voucher_series_services.py
fortnox/services/price_list_services.py
fortnox/services/price_services.py
fortnox/services/print_template_services.py
fortnox/services/project_services.py
fortnox/services/salary_transaction_services.py
fortnox/services/schedule_time_services.py
fortnox/services/sie_services.py
fortnox/services/supplier_invoice_accrual_services.py
pyfortnox-1.2.0.dist-info/LICENSE
pyfortnox-1.2.0.dist-info/METADATA
pyfortnox-1.2.0.dist-info/WHEEL
pyfortnox-1.2.0.dist-info/top_level.txt
pyfortnox-1.2.0.dist-info/RECORD
