Metadata-Version: 2.1
Name: pyfortnox
Version: 1.2.0
Summary: Fortnox API V3 library client for Python
Home-page: https://github.com/xalien10/pyfortnox
Author: Mahmudul Hasan
Author-email: ikhtiarcse10ruet@gmail.com
License: UNKNOWN
Platform: UNKNOWN
Classifier: Programming Language :: Python :: 3
Classifier: License :: OSI Approved :: MIT License
Classifier: Operating System :: OS Independent
Requires-Python: >=3.6
Requires-Dist: munch (>=2.5.0)
Requires-Dist: requests (>=2.21.0)
Requires-Dist: urllib3 (>=1.24.3)
Requires-Dist: requests-toolbelt (>=0.9.1)
